Metadata-Version: 2.1
Name: alphalens
Version: 0.4.0
Summary: Performance analysis of predictive (alpha) stock factors
Home-page: https://github.com/quantopian/alphalens
Author: Quantopian Inc.
Author-email: opensource@quantopian.com
License: UNKNOWN
Platform: UNKNOWN
Classifier: Development Status :: 5 - Production/Stable
Classifier: Intended Audience :: Developers
Classifier: License :: OSI Approved :: Apache Software License
Classifier: Natural Language :: English
Classifier: Operating System :: OS Independent
Classifier: Programming Language :: Python :: 2.7
Classifier: Programming Language :: Python :: 3.4
Classifier: Programming Language :: Python :: 3.5
Classifier: Programming Language :: Python
Classifier: Topic :: Utilities
Classifier: Topic :: Office/Business :: Financial
Classifier: Topic :: Scientific/Engineering :: Information Analysis
Provides-Extra: test
